ccapi/VERSION
ccapi/__attr__.py
ccapi/__init__.py
ccapi/__main__.py
ccapi/_compat.py
ccapi/ccapi.py
ccapi/config.py
ccapi/constant.py
ccapi/exception.py
ccapi/template.py
ccapi/api/__init__.py
ccapi/api/client.py
ccapi/api/helper.py
ccapi/cli/__init__.py
ccapi/cli/parser.py
ccapi/commands/__init__.py
ccapi/commands/helper.py
ccapi/commands/util/__init__.py
ccapi/core/__init__.py
ccapi/core/config.py
ccapi/core/querylist.py
ccapi/core/singleton.py
ccapi/core/mixins/__init__.py
ccapi/data/bootstrap.sql
ccapi/data/models/boolean/json/sample.json
ccapi/data/models/boolean/sbml/fibroblasts.sbml
ccapi/data/models/boolean/sbml/lac-operon.sbml
ccapi/data/models/boolean/yaml/sample.yaml
ccapi/data/models/metabolic/json/stm_1.0.json
ccapi/data/models/metabolic/sbml/dehalococcoides.sbml
ccapi/data/templates/model.html
ccapi/data/templates/test.html
ccapi/data/templates/user.html
ccapi/data/templates/boolean/model.html
ccapi/data/templates/boolean/component/internal.html
ccapi/data/templates/metabolic/model.html
ccapi/io/__init__.py
ccapi/io/_json.py
ccapi/io/_pickle.py
ccapi/io/_yaml.py
ccapi/jobs/__init__.py
ccapi/model/__init__.py
ccapi/model/document.py
ccapi/model/resource.py
ccapi/model/user.py
ccapi/model/util.py
ccapi/model/model/__init__.py
ccapi/model/model/activity.py
ccapi/model/model/base.py
ccapi/model/model/species.py
ccapi/model/model/version.py
ccapi/model/model/boolean/__init__.py
ccapi/model/model/boolean/component.py
ccapi/model/model/boolean/operator.py
ccapi/model/model/boolean/regulator.py
ccapi/model/model/boolean/condition/__init__.py
ccapi/model/model/boolean/condition/relation.py
ccapi/model/model/boolean/condition/state.py
ccapi/model/model/boolean/condition/type.py
ccapi/model/model/education/__init__.py
ccapi/model/model/education/activity.py
ccapi/model/model/education/module.py
ccapi/model/model/education/question.py
ccapi/model/model/kinetic/__init__.py
ccapi/model/model/metabolic/__init__.py
ccapi/model/model/metabolic/gene.py
ccapi-0.1.0.dist-info/AUTHORS.md
ccapi-0.1.0.dist-info/LICENSE
ccapi-0.1.0.dist-info/METADATA
ccapi-0.1.0.dist-info/WHEEL
ccapi-0.1.0.dist-info/entry_points.txt
ccapi-0.1.0.dist-info/top_level.txt
ccapi-0.1.0.dist-info/RECORD
