Metadata-Version: 2.1
Name: ccapi
Version: 0.1.0
Summary: Python API for Cell Collective
Home-page: https://github.com/cellcollective/ccapi
Author: Achilles Rasquinha
Author-email: achillesrasquinha@gmail.com
License: MIT License
Keywords: ccapi model cell collective
Classifier: Development Status :: 5 - Production/Stable
Classifier: Environment :: Console
Classifier: Intended Audience :: Developers
Classifier: License :: OSI Approved :: MIT License
Classifier: Programming Language :: Python :: 2
Classifier: Programming Language :: Python :: 2.7
Classifier: Programming Language :: Python :: 3
Classifier: Programming Language :: Python :: 3.4
Classifier: Programming Language :: Python :: 3.5
Classifier: Programming Language :: Python :: 3.6
Classifier: Programming Language :: Python :: 3.7
Classifier: Programming Language :: Python :: 3.8
Classifier: Programming Language :: Python :: 3.9
Classifier: Programming Language :: Python :: 3.10
Classifier: Programming Language :: Python :: Implementation :: CPython
Classifier: Programming Language :: Python :: Implementation :: PyPy
License-File: LICENSE
License-File: AUTHORS.md
Requires-Dist: requests
Requires-Dist: grequests
Requires-Dist: requests-cache
Requires-Dist: python-socketio[client]
Requires-Dist: bpyutils
Provides-Extra: dev
Requires-Dist: matplotlib ; extra == 'dev'
Requires-Dist: networkx ; extra == 'dev'
Requires-Dist: sphinx ; extra == 'dev'
Requires-Dist: recommonmark ; extra == 'dev'
Requires-Dist: sphinx-autobuild ; extra == 'dev'
Requires-Dist: ipykernel ; extra == 'dev'
Requires-Dist: nbsphinx ; extra == 'dev'
Requires-Dist: pylint ; extra == 'dev'
Requires-Dist: autopep8 ; extra == 'dev'
Requires-Dist: pytest ; extra == 'dev'
Requires-Dist: pytest-cov ; extra == 'dev'
Requires-Dist: pytest-xdist ; extra == 'dev'
Requires-Dist: pytest-sugar ; extra == 'dev'
Requires-Dist: tox ; extra == 'dev'
Requires-Dist: coveralls ; extra == 'dev'
Requires-Dist: pluggy (<1,>=0.12.0) ; extra == 'dev'
Requires-Dist: docstr-coverage ; extra == 'dev'
Requires-Dist: pipenv ; extra == 'dev'
Requires-Dist: jedi (<0.18) ; extra == 'dev'
Requires-Dist: ipython ; extra == 'dev'
Requires-Dist: bumpversion ; extra == 'dev'
Requires-Dist: vulture ; extra == 'dev'
Requires-Dist: safety ; extra == 'dev'
Requires-Dist: pre-commit ; extra == 'dev'
Requires-Dist: twine ; extra == 'dev'
Requires-Dist: jupyter ; extra == 'dev'
Requires-Dist: Flask ; extra == 'dev'
